MANIFEST.in
README.rst
setup.py
tailbone_theo.egg-info/PKG-INFO
tailbone_theo.egg-info/SOURCES.txt
tailbone_theo.egg-info/dependency_links.txt
tailbone_theo.egg-info/entry_points.txt
tailbone_theo.egg-info/requires.txt
tailbone_theo.egg-info/top_level.txt
theo/__init__.py
theo/_version.py
theo/appsettings.py
theo/config.py
theo/db/__init__.py
theo/db/model_catapult.py
theo/db/model_corepos.py
theo/db/model_locsms.py
theo/emails/__init__.py
theo/emails/catapult.py
theo/emails/corepos.py
theo/emails/locsms.py
theo/emails/theo.py
theo/importing/__init__.py
theo/importing/versions_catapult.py
theo/importing/versions_corepos.py
theo/importing/versions_locsms.py
theo/web/__init__.py
theo/web/app.py
theo/web/menus.py
theo/web/subscribers.py
theo/web/static/__init__.py
theo/web/templates/base_meta.mako
theo/web/views/__init__.py
theo/web/views/common.py