Metadata-Version: 2.1
Name: tailbone-theo
Version: 0.1.6
Summary: Theo, the order system
Home-page: https://rattailproject.org
Author: Lance Edgar
Author-email: lance@edbob.org
License: UNKNOWN
Platform: UNKNOWN
Classifier: Development Status :: 3 - Alpha
Classifier: Environment :: Console
Classifier: Environment :: Web Environment
Classifier: Framework :: Pyramid
Classifier: Intended Audience :: Developers
Classifier: Natural Language :: English
Classifier: Operating System :: POSIX :: Linux
Classifier: Programming Language :: Python
Classifier: Programming Language :: Python :: 3
Classifier: Topic :: Office/Business
Provides-Extra: fabric
Provides-Extra: app
Provides-Extra: catapult
Provides-Extra: locsms
Provides-Extra: corepos
